gpyutils/__init__.py
gpyutils/ansi.py
gpyutils/eclasses.py
gpyutils/implementations.py
gpyutils/packages.py
gpyutils/pycompat.py
gpyutils/scripts/__init__.py
gpyutils/scripts/depgraph.py
gpyutils/scripts/drop_dead_impls.py
gpyutils/scripts/impl.py
gpyutils/scripts/junit2deselect.py
gpyutils/scripts/list_pkg_impls.py
gpyutils/scripts/pkgs_with_newest_stable.py
gpyutils/scripts/release_feed_opml.py
gpyutils/scripts/showimpls.py
gpyutils/scripts/to_pypi_eclass.py
gpyutils/scripts/upgrade_impl.py
gpyutils/scripts/verify_deps.py
gpyutils-0.15.0.dist-info/entry_points.txt
gpyutils-0.15.0.dist-info/licenses/COPYING
gpyutils-0.15.0.dist-info/WHEEL
gpyutils-0.15.0.dist-info/METADATA
gpyutils-0.15.0.dist-info/RECORD
