Metadata-Version: 2.4
Name: gpyutils
Version: 0.15.0
Summary: Maintenance scripts for Gentoo Python packages
Author-email: Michał Górny <mgorny@gentoo.org>
Requires-Python: >=3.11
Classifier: Development Status :: 4 - Beta
Classifier: Environment :: Console
Classifier: Intended Audience :: System Administrators
Classifier: License :: OSI Approved :: GNU General Public License v2 or later (GPLv2+)
Classifier: Operating System :: POSIX
Classifier: Programming Language :: Python
Classifier: Topic :: System :: Installation/Setup
License-File: COPYING
Requires-Dist: gentoopm
Requires-Dist: networkx ; extra == "depgraph-nx"
Requires-Dist: lxml ; extra == "release-feed-opml"
Requires-Dist: lxml ; extra == "test"
Requires-Dist: packaging ; extra == "test"
Requires-Dist: pytest ; extra == "test"
Requires-Dist: packaging ; extra == "verify-deps"
Project-URL: Homepage, https://github.com/mgorny/gpyutils/
Provides-Extra: depgraph-nx
Provides-Extra: release-feed-opml
Provides-Extra: test
Provides-Extra: verify-deps
